web3py_ext/__init__.py
web3py_ext/extend.py
web3py_ext/klaytn_account/__init__.py
web3py_ext/klaytn_account/account_key.py
web3py_ext/klaytn_account/account_store.py
web3py_ext/klaytn_account/instrumented_local_account.py
web3py_ext/klaytn_account/middleware.py
web3py_ext/klaytn_account/utils.py
web3py_ext/transaction/__init__.py
web3py_ext/transaction/extended_transaction_utils.py
web3py_ext/transaction/transaction.py
web3py_ext/transaction/wrapper_typed_transaction.py
web3py_ext/transaction/basic/__init__.py
web3py_ext/transaction/basic/account_update_transaction.py
web3py_ext/transaction/basic/cancel_transaction.py
web3py_ext/transaction/basic/chaindata_anchoring_transaction.py
web3py_ext/transaction/basic/smart_contract_deploy_transaction.py
web3py_ext/transaction/basic/smart_contract_execution_transaction.py
web3py_ext/transaction/basic/value_transfer_transaction.py
web3py_ext/transaction/basic/value_transfer_with_memo_transaction.py
web3py_ext/transaction/fee_delegation/__init__.py
web3py_ext/transaction/fee_delegation/fee_delegated_account_update_transaction.py
web3py_ext/transaction/fee_delegation/fee_delegated_cancel_transaction.py
web3py_ext/transaction/fee_delegation/fee_delegated_chaindata_anchoring_transaction.py
web3py_ext/transaction/fee_delegation/fee_delegated_smart_contract_deploy_transaction.py
web3py_ext/transaction/fee_delegation/fee_delegated_smart_contract_execution_transaction.py
web3py_ext/transaction/fee_delegation/fee_delegated_value_transfer_transaction.py
web3py_ext/transaction/fee_delegation/fee_delegated_value_transfer_with_memo_transaction.py
web3py_ext/transaction/partial_fee_delegation/__init__.py
web3py_ext/utils/__init__.py
web3py_ext/utils/klaytn_utils.py
web3py_ext/web3rpc/__init__.py
web3py_ext/web3rpc/admin_api.py
web3py_ext/web3rpc/debug_api.py
web3py_ext/web3rpc/governance_api.py
web3py_ext/web3rpc/klay_api.py
web3py_ext/web3rpc/mainbridge_api.py
web3py_ext/web3rpc/net_api.py
web3py_ext/web3rpc/personal_api.py
web3py_ext-2.1.0.dist-info/METADATA
web3py_ext-2.1.0.dist-info/WHEEL
web3py_ext-2.1.0.dist-info/top_level.txt
web3py_ext-2.1.0.dist-info/RECORD
