Metadata-Version: 2.1
Name: web3py-ext
Version: 2.1.0
Summary: kaia-sdk
Home-page: https://github.com/kaiachain/kaia-sdk
Author: kaia Foundation
Author-email: 
License: MIT
Keywords: kaia,klaytn,ethereum,role-based,multisig
Requires-Python: >=3.7
Requires-Dist: eth-account ~=0.11.2
Requires-Dist: web3 ~=6.3.0
